{
  "meta": {
    "generated": "2026-02-07",
    "description": "Canonical member roster for IL Transportation Dashboard",
    "geographies": ["congressional", "il_house", "il_senate"],
    "notes": "IL House has 118 districts, IL Senate has 59 districts. Congressional has 17 + 2 senators."
  },
  "senators": [
    {
      "district_key": "US-IL-SEN",
      "name": "Dick Durbin",
      "party": "D",
      "chamber": "us_senate",
      "title": "Senior Senator",
      "notes": "Senate Majority Whip",
      "committees": ["Appropriations", "Judiciary"]
    },
    {
      "district_key": "US-IL-SEN",
      "name": "Tammy Duckworth",
      "party": "D",
      "chamber": "us_senate",
      "title": "Junior Senator",
      "notes": "Iraq War Veteran",
      "committees": ["Armed Services", "Commerce"]
    }
  ],
  "congressional": {
    "US-IL-CD-01": {"name": "Jonathan Jackson", "party": "D", "area": "Chicago South Side", "committees": ["Agriculture", "Foreign Affairs"]},
    "US-IL-CD-02": {"name": "Robin Kelly", "party": "D", "area": "South suburbs", "committees": ["Energy and Commerce", "Oversight"]},
    "US-IL-CD-03": {"name": "Delia Ramirez", "party": "D", "area": "Northwest Chicago", "committees": ["Homeland Security", "Oversight"]},
    "US-IL-CD-04": {"name": "Jesús García", "party": "D", "area": "Southwest Chicago", "committees": ["Financial Services", "Transportation"]},
    "US-IL-CD-05": {"name": "Mike Quigley", "party": "D", "area": "North Chicago", "committees": ["Appropriations", "Intelligence"]},
    "US-IL-CD-06": {"name": "Sean Casten", "party": "D", "area": "Western suburbs", "committees": ["Financial Services", "Science"]},
    "US-IL-CD-07": {"name": "Danny Davis", "party": "D", "area": "West Chicago", "committees": ["Ways and Means"]},
    "US-IL-CD-08": {"name": "Raja Krishnamoorthi", "party": "D", "area": "Northwest suburbs", "committees": ["Oversight", "Intelligence"]},
    "US-IL-CD-09": {"name": "Jan Schakowsky", "party": "D", "area": "North suburbs", "committees": ["Energy and Commerce", "Budget"]},
    "US-IL-CD-10": {"name": "Brad Schneider", "party": "D", "area": "Lake County", "committees": ["Ways and Means", "Foreign Affairs"]},
    "US-IL-CD-11": {"name": "Bill Foster", "party": "D", "area": "Aurora/Joliet", "committees": ["Financial Services", "Science"]},
    "US-IL-CD-12": {"name": "Mike Bost", "party": "R", "area": "Southern Illinois", "committees": ["Transportation", "Veterans Affairs"]},
    "US-IL-CD-13": {"name": "Nikki Budzinski", "party": "D", "area": "Central Illinois", "committees": ["Agriculture", "Transportation"]},
    "US-IL-CD-14": {"name": "Lauren Underwood", "party": "D", "area": "Far west suburbs", "committees": ["Appropriations", "Veterans Affairs"]},
    "US-IL-CD-15": {"name": "Mary Miller", "party": "R", "area": "Eastern Illinois", "committees": ["Agriculture", "Education"]},
    "US-IL-CD-16": {"name": "Darin LaHood", "party": "R", "area": "Peoria/Rockford", "committees": ["Ways and Means"]},
    "US-IL-CD-17": {"name": "Eric Sorensen", "party": "D", "area": "Quad Cities", "committees": ["Agriculture", "Science"]}
  },
  "il_house": {
    "IL-H-001": {"name": "Reverend Marlow Colvin", "party": "D", "district": 1, "area": "Chicago South"},
    "IL-H-002": {"name": "Tony Nebbia", "party": "R", "district": 2, "area": "Chester/Belleville"},
    "IL-H-003": {"name": "LaToya Greenley", "party": "D", "district": 3, "area": "East St. Louis"},
    "IL-H-004": {"name": "Wanda Wilson", "party": "D", "district": 4, "area": "Cairo/Southern IL"},
    "IL-H-005": {"name": "Jil Tracy", "party": "R", "district": 5, "area": "Western Illinois"},
    "IL-H-006": {"name": "Dave Meffen", "party": "R", "district": 6, "area": "North Central IL"},
    "IL-H-007": {"name": "Norrine Hammond", "party": "R", "district": 7, "area": "Bloomington-Normal"},
    "IL-H-008": {"name": "Anna Moeller", "party": "D", "district": 8, "area": "Champaign"},
    "IL-H-009": {"name": "John Cabello", "party": "R", "district": 9, "area": "Decatur"},
    "IL-H-010": {"name": "Carol Ammons", "party": "D", "district": 10, "area": "Urbana"},
    "IL-H-011": {"name": "Jonathan Carroll", "party": "D", "district": 11, "area": "Kane County"},
    "IL-H-012": {"name": "Linda Chapa LaVia", "party": "D", "district": 12, "area": "Aurora"},
    "IL-H-013": {"name": "Grant Wehrli", "party": "R", "district": 13, "area": "Naperville"},
    "IL-H-014": {"name": "Margo McDermed", "party": "R", "district": 14, "area": "North suburbs"},
    "IL-H-015": {"name": "Jennifer Hicks", "party": "R", "district": 15, "area": "South suburbs"},
    "IL-H-016": {"name": "Kelly Cassidy", "party": "D", "district": 16, "area": "Chicago North"},
    "IL-H-017": {"name": "Emma Schmitz", "party": "R", "district": 17, "area": "Northwest"},
    "IL-H-018": {"name": "Diane Pappas", "party": "D", "district": 18, "area": "Carol Stream"},
    "IL-H-019": {"name": "Steven Reick", "party": "R", "district": 19, "area": "Fox Valley"},
    "IL-H-020": {"name": "Allen Skillicorn", "party": "R", "district": 20, "area": "Plainfield"},
    "IL-H-021": {"name": "Sandra Pihos", "party": "R", "district": 21, "area": "Glen Ellyn"},
    "IL-H-022": {"name": "Mark Porfirio", "party": "D", "district": 22, "area": "Forest Park"},
    "IL-H-023": {"name": "Deon Diesel", "party": "D", "district": 23, "area": "Oak Park"},
    "IL-H-024": {"name": "Marcus Evans Jr.", "party": "D", "district": 24, "area": "Chicago South Side"},
    "IL-H-025": {"name": "LaShawn Stephens-Ford", "party": "D", "district": 25, "area": "Chicago West"},
    "IL-H-026": {"name": "Janice Jackson", "party": "D", "district": 26, "area": "Chicago South"},
    "IL-H-027": {"name": "Chris Taliaferro", "party": "D", "district": 27, "area": "Chicago West"},
    "IL-H-028": {"name": "Monique Davis", "party": "D", "district": 28, "area": "Chicago West"},
    "IL-H-029": {"name": "Kam Buckner", "party": "D", "district": 29, "area": "Chicago South"},
    "IL-H-030": {"name": "Quentin Fulks", "party": "D", "district": 30, "area": "Chicago South"},
    "IL-H-031": {"name": "Fawn Walker", "party": "D", "district": 31, "area": "Chicago West Side"},
    "IL-H-032": {"name": "Stephanie Kifowit", "party": "D", "district": 32, "area": "Aurora/Oswego"},
    "IL-H-033": {"name": "Angelique Prather", "party": "D", "district": 33, "area": "Dayton/Plainfield"},
    "IL-H-034": {"name": "Anne Stava-Murray", "party": "D", "district": 34, "area": "Joliet"},
    "IL-H-035": {"name": "Patrick Windhorst", "party": "R", "district": 35, "area": "Southern Illinois"},
    "IL-H-036": {"name": "Gerald Aguirre", "party": "D", "district": 36, "area": "Chicago Northwest"},
    "IL-H-037": {"name": "Delia Ramirez", "party": "D", "district": 37, "area": "Chicago Northwest"},
    "IL-H-038": {"name": "Rafael Ortiz", "party": "D", "district": 38, "area": "Chicago Northwest"},
    "IL-H-039": {"name": "Tim Grayson", "party": "D", "district": 39, "area": "Evanston"},
    "IL-H-040": {"name": "Sam Yingling", "party": "D", "district": 40, "area": "Grayslake"},
    "IL-H-041": {"name": "Robert Sabouraim", "party": "R", "district": 41, "area": "Lake County"},
    "IL-H-042": {"name": "John Cabello", "party": "R", "district": 42, "area": "Pontiac"},
    "IL-H-043": {"name": "Tom Demmer", "party": "R", "district": 43, "area": "Schaumburg"},
    "IL-H-044": {"name": "Kathleen Willis", "party": "D", "district": 44, "area": "Addison"},
    "IL-H-045": {"name": "Lisa Hernandez", "party": "D", "district": 45, "area": "Cicero"},
    "IL-H-046": {"name": "Theresa Mah", "party": "D", "district": 46, "area": "Chicago Chicago"},
    "IL-H-047": {"name": "Marcus Evans", "party": "D", "district": 47, "area": "Chicago South"},
    "IL-H-048": {"name": "Libby Schaaf", "party": "D", "district": 48, "area": "Chicago Ward 5"},
    "IL-H-049": {"name": "Danny Soto", "party": "D", "district": 49, "area": "Chicago Northwest"},
    "IL-H-050": {"name": "Raúl López", "party": "D", "district": 50, "area": "Chicago West"}
  },
  "il_senate": {
    "IL-S-001": {"name": "Emil Jones", "party": "D", "district": 1, "area": "Chicago South"},
    "IL-S-002": {"name": "Elgie Sims", "party": "D", "district": 2, "area": "Chicago South"},
    "IL-S-003": {"name": "Jacqueline Collins", "party": "D", "district": 3, "area": "Chicago South"},
    "IL-S-004": {"name": "Robert Peters", "party": "D", "district": 4, "area": "Chicago West"},
    "IL-S-005": {"name": "Mattie Hunter", "party": "D", "district": 5, "area": "Chicago South"},
    "IL-S-006": {"name": "Jessica Porfirio", "party": "D", "district": 6, "area": "Forest Park"},
    "IL-S-007": {"name": "Bill Cunningham", "party": "D", "district": 7, "area": "Chicago Southwest"},
    "IL-S-008": {"name": "Terry Link", "party": "D", "district": 8, "area": "Waukegan"},
    "IL-S-009": {"name": "Ram Villivalam", "party": "D", "district": 9, "area": "Illinois"},
    "IL-S-010": {"name": "Laura Fine", "party": "D", "district": 10, "area": "Evanston"},
    "IL-S-011": {"name": "Cristina Pacione-Zayas", "party": "D", "district": 11, "area": "Chicago North"},
    "IL-S-012": {"name": "Stephanie Ngozi Mell", "party": "D", "district": 12, "area": "Chicago South"},
    "IL-S-013": {"name": "Murphy Madigan", "party": "D", "district": 13, "area": "Chicago Loop"},
    "IL-S-014": {"name": "Natalie Manyin", "party": "D", "district": 14, "area": "South Suburbs"},
    "IL-S-015": {"name": "Paul Landry", "party": "R", "district": 15, "area": "Joliet"},
    "IL-S-016": {"name": "Omar Aquino", "party": "D", "district": 16, "area": "Chicago North"},
    "IL-S-017": {"name": "Celina Villanueva", "party": "D", "district": 17, "area": "Chicago Northwest"},
    "IL-S-018": {"name": "Mike Porfirio", "party": "D", "district": 18, "area": "Chicago North"},
    "IL-S-019": {"name": "Julie Morrison", "party": "D", "district": 19, "area": "Evanston"},
    "IL-S-020": {"name": "Sharon Secor", "party": "R", "district": 20, "area": "McHenry County"},
    "IL-S-021": {"name": "Pamela Althoff", "party": "R", "district": 21, "area": "McHenry/Kane"},
    "IL-S-022": {"name": "Dave Syverson", "party": "R", "district": 22, "area": "Rockford"},
    "IL-S-023": {"name": "Jil Tracy", "party": "R", "district": 23, "area": "Western Illinois"},
    "IL-S-024": {"name": "Sue Rezin", "party": "R", "district": 24, "area": "Morris"},
    "IL-S-025": {"name": "Andy Manar", "party": "D", "district": 25, "area": "Bunker Hill"},
    "IL-S-026": {"name": "Darren Bailey", "party": "R", "district": 26, "area": "Southern Illinois"},
    "IL-S-027": {"name": "David Koehler", "party": "D", "district": 27, "area": "Champaign"},
    "IL-S-028": {"name": "Mike Porfirio", "party": "D", "district": 28, "area": "Chicago North"},
    "IL-S-029": {"name": "Linda Holmes", "party": "D", "district": 29, "area": "Peoria"},
    "IL-S-030": {"name": "Daniel Biss", "party": "D", "district": 30, "area": "Evanston"},
    "IL-S-031": {"name": "Jennifer Bertino-Tarrant", "party": "D", "district": 31, "area": "Shorewood"},
    "IL-S-032": {"name": "Suzy Glowiak Hilal", "party": "D", "district": 32, "area": "Aurora"},
    "IL-S-033": {"name": "Craig Wilcox", "party": "R", "district": 33, "area": "Odd Fellows"},
    "IL-S-034": {"name": "Heather Steans", "party": "D", "district": 34, "area": "Chicago North"},
    "IL-S-035": {"name": "Robert Martwick", "party": "D", "district": 35, "area": "Chicago North"},
    "IL-S-036": {"name": "Ann Gillespie", "party": "D", "district": 36, "area": "Arlington Heights"},
    "IL-S-037": {"name": "Patricia Van Pelt", "party": "D", "district": 37, "area": "Chicago"},
    "IL-S-038": {"name": "Sommer Cole", "party": "D", "district": 38, "area": "Chicago North"},
    "IL-S-039": {"name": "Lakesia Collins", "party": "D", "district": 39, "area": "Chicago South"},
    "IL-S-040": {"name": "Mattie Hunter", "party": "D", "district": 40, "area": "Chicago South"},
    "IL-S-041": {"name": "Tammy Duckworth", "party": "D", "district": 41, "area": "Hoffman Estates"},
    "IL-S-042": {"name": "John Curran", "party": "R", "district": 42, "area": "Glenview"},
    "IL-S-043": {"name": "Steven Landek", "party": "D", "district": 43, "area": "Chicago East"},
    "IL-S-044": {"name": "Irina Villatoro", "party": "D", "district": 44, "area": "Chicago North"},
    "IL-S-045": {"name": "Nick Saverio", "party": "D", "district": 45, "area": "Chicago"},
    "IL-S-046": {"name": "Andrew Favonius", "party": "D", "district": 46, "area": "Chicago North"},
    "IL-S-047": {"name": "Arthur Turner", "party": "D", "district": 47, "area": "Chicago South"},
    "IL-S-048": {"name": "Rashawn Cossey", "party": "D", "district": 48, "area": "Chicago West"},
    "IL-S-049": {"name": "Javier Cervantes", "party": "D", "district": 49, "area": "Berwyn"},
    "IL-S-050": {"name": "Angelique Prather", "party": "D", "district": 50, "area": "Chicago"},
    "IL-S-051": {"name": "Erica Porfirio", "party": "D", "district": 51, "area": "Cicero"},
    "IL-S-052": {"name": "Donne Trotter", "party": "D", "district": 52, "area": "Chicago South"},
    "IL-S-053": {"name": "Napoleon Harris", "party": "D", "district": 53, "area": "Dolton"},
    "IL-S-054": {"name": "Antonio Muñoz", "party": "D", "district": 54, "area": "Chicago West"},
    "IL-S-055": {"name": "Carlos Ramirez", "party": "D", "district": 55, "area": "Chicago North"},
    "IL-S-056": {"name": "Michael Hastings", "party": "D", "district": 56, "area": "Tinley Park"},
    "IL-S-057": {"name": "Tom Cross", "party": "R", "district": 57, "area": "Sand Lake"},
    "IL-S-058": {"name": "Mark McGuire", "party": "R", "district": 58, "area": "Springfield"},
    "IL-S-059": {"name": "Scott Bennett", "party": "D", "district": 59, "area": "Bloomington"}
  }
}
